django_systemjs-1.4.3.data/scripts/trace-deps.js
django_systemjs-1.4.3.dist-info/DESCRIPTION.rst
django_systemjs-1.4.3.dist-info/METADATA
django_systemjs-1.4.3.dist-info/RECORD
django_systemjs-1.4.3.dist-info/WHEEL
django_systemjs-1.4.3.dist-info/metadata.json
django_systemjs-1.4.3.dist-info/top_level.txt
systemjs/__init__.py
systemjs/apps.py
systemjs/base.py
systemjs/compat.py
systemjs/conf.py
systemjs/finders.py
systemjs/jspm.py
systemjs/storage.py
systemjs/management/__init__.py
systemjs/management/commands/__init__.py
systemjs/management/commands/_mixins.py
systemjs/management/commands/systemjs_bundle.py
systemjs/management/commands/systemjs_show_packages.py
systemjs/management/commands/systemjs_write_depcaches.py
systemjs/templatetags/__init__.py
systemjs/templatetags/system_tags.py
