Metadata-Version: 2.0
Name: django-systemjs
Version: 1.4.3
Summary: Brings SystemJS to Django staticfiles
Home-page: https://github.com/sergei-maertens/django-systemjs
Author: Sergei Maertens
Author-email: sergeimaertens@gmail.com
License: MIT
Platform: any
Classifier: Development Status :: 5 - Production/Stable
Classifier: Framework :: Django :: 1.8
Classifier: Framework :: Django :: 1.9
Classifier: Intended Audience :: Developers
Classifier: Operating System :: Unix
Classifier: Operating System :: MacOS
Classifier: Operating System :: Microsoft :: Windows
Classifier: Programming Language :: Python :: 2.7
Classifier: Programming Language :: Python :: 3.3
Classifier: Programming Language :: Python :: 3.4
Classifier: Programming Language :: Python :: 3.5
Classifier: Topic :: Software Development :: Libraries :: Application Frameworks
Requires-Dist: django-appconf (>=0.6)
Requires-Dist: semantic-version
Provides-Extra: test
Requires-Dist: mock; extra == 'test'
Requires-Dist: coverage; extra == 'test'
